qchecker/__init__.py
qchecker/match.py
qchecker/parser.py
qchecker/descriptions/__init__.py
qchecker/descriptions/_descriptions.py
qchecker/descriptions/descriptions.toml
qchecker/general/__init__.py
qchecker/general/_flake8_checks.py
qchecker/general/_process.py
qchecker/general/_pylint_checks.py
qchecker/substructures/__init__.py
qchecker/substructures/_ast_substructures.py
qchecker/substructures/_base.py
qchecker/substructures/_cst_substructures.py
qchecker-1.1.2.dist-info/LICENSE
qchecker-1.1.2.dist-info/METADATA
qchecker-1.1.2.dist-info/WHEEL
qchecker-1.1.2.dist-info/top_level.txt
qchecker-1.1.2.dist-info/RECORD
