Metadata-Version: 2.1
Name: qchecker
Version: 1.1.2
Summary: A simple library for finding statement-level substructures in Abstract Syntax Trees
Home-page: https://github.com/James-Ansley/qchecker
Author: James Finnie-Ansley
License: MIT License
Classifier: Development Status :: 5 - Production/Stable
Classifier: Topic :: Utilities
Classifier: Intended Audience :: Developers
Classifier: Programming Language :: Python :: 3
Classifier: License :: OSI Approved :: MIT License
Classifier: Operating System :: OS Independent
Requires-Python: >=3.10
License-File: LICENSE
Requires-Dist: tomli (~=2.0.1)
Requires-Dist: libcst (~=0.4.1)
Requires-Dist: Deprecated (~=1.2.13)
Provides-Extra: general_checks
Requires-Dist: pylint (~=2.13.5) ; extra == 'general_checks'
Requires-Dist: flake8 (~=4.0.1) ; extra == 'general_checks'
Requires-Dist: flake8-json (~=21.7.0) ; extra == 'general_checks'
